sumo/__init__.py
sumo/wrapper/__init__.py
sumo/wrapper/_auth_provider.py
sumo/wrapper/_blob_client.py
sumo/wrapper/_decorators.py
sumo/wrapper/_logging.py
sumo/wrapper/_retry_strategy.py
sumo/wrapper/_version.py
sumo/wrapper/config.py
sumo/wrapper/login.py
sumo/wrapper/sumo_client.py
sumo_wrapper_python-1.3.0.dist-info/licenses/LICENSE
sumo_wrapper_python-1.3.0.dist-info/METADATA
sumo_wrapper_python-1.3.0.dist-info/WHEEL
sumo_wrapper_python-1.3.0.dist-info/entry_points.txt
sumo_wrapper_python-1.3.0.dist-info/top_level.txt
sumo_wrapper_python-1.3.0.dist-info/RECORD
