Metadata-Version: 2.4
Name: sumo-wrapper-python
Version: 1.3.0
Summary: Python wrapper for the Sumo API
Author: Equinor
License:                                  Apache License
Project-URL: Repository, https://github.com/equinor/sumo-wrapper-python
Classifier: License :: OSI Approved :: Apache Software License
Classifier: Programming Language :: Python
Requires-Python: >=3.11
License-File: LICENSE
Requires-Dist: msal>=1.20.0
Requires-Dist: msal-extensions>=1.0.0
Requires-Dist: pyjwt>=2.4.0
Requires-Dist: httpx>=0.24.1
Requires-Dist: tenacity!=8.4.0,>=8.2.2
Requires-Dist: azure-identity>=1.13.0
Provides-Extra: test
Requires-Dist: pytest; extra == "test"
Requires-Dist: PyYAML; extra == "test"
Provides-Extra: docs
Requires-Dist: sphinx==7.1.2; extra == "docs"
Requires-Dist: sphinx-rtd-theme; extra == "docs"
Requires-Dist: autoapi; extra == "docs"
Requires-Dist: sphinx-autodoc-typehints; extra == "docs"
Requires-Dist: sphinxcontrib-apidoc; extra == "docs"
Provides-Extra: dev
Requires-Dist: ruff; extra == "dev"
Requires-Dist: pre-commit; extra == "dev"
Dynamic: license-file
